{
  "gallery": [
    {
      "name": "",
      "picture": "/jpg/gallery/gallery_01.jpg"
    },
    {
      "name": "",
      "picture": "/jpg/gallery/gallery_02.jpg"
    },
    {
      "name": "",
      "picture": "/jpg/gallery/gallery_03.jpg"
    },
    {
      "name": "",
      "picture": "/jpg/gallery/gallery_04.jpg"
    },
    {
      "name": "",
      "picture": "/jpg/gallery/gallery_05.jpg"
    },
    {
      "name": "",
      "picture": "/jpg/gallery/gallery_06.jpg"
    },
    {
      "name": "",
      "picture": "/jpg/gallery/gallery_07.jpg"
    },
    {
      "name": "",
      "picture": "/jpg/gallery/gallery_08.jpg"
    },
    {
      "name": "",
      "picture": "/jpg/gallery/gallery_09.jpg"
    },
    {
      "name": "",
      "picture": "/jpg/gallery/gallery_10.jpg"
    },
    {
      "name": "",
      "picture": "/jpg/gallery/gallery_11.jpg"
    },
    {
      "name": "",
      "picture": "/jpg/gallery/gallery_12.jpg"
    },
    {
      "name": "",
      "picture": "/jpg/gallery/gallery_13.jpg"
    },
    {
      "name": "",
      "picture": "/jpg/gallery/gallery_14.jpg"
    },
    {
      "name": "",
      "picture": "/jpg/gallery/gallery_15.jpg"
    },
    {
      "name": "",
      "picture": "/jpg/gallery/gallery_16.jpg"
    },
    {
      "name": "",
      "picture": "/jpg/gallery/gallery_17.jpg"
    },
    {
      "name": "",
      "picture": "/jpg/gallery/gallery_18.jpg"
    },
    {
      "name": "",
      "picture": "/jpg/gallery/gallery_19.jpg"
    },
    {
      "name": "",
      "picture": "/jpg/gallery/gallery_20.jpg"
    },
    {
      "name": "",
      "picture": "/jpg/gallery/gallery_21.jpg"
    },
    {
      "name": "",
      "picture": "/jpg/gallery/gallery_22.jpg"
    },
    {
      "name": "",
      "picture": "/jpg/gallery/gallery_23.jpg"
    },
    {
      "name": "",
      "picture": "/jpg/gallery/gallery_26.jpg"
    },
    {
      "name": "",
      "picture": "/jpg/gallery/gallery_27.jpg"
    },
    {
      "name": "",
      "picture": "/jpg/gallery/gallery_28.jpg"
    },
    {
      "name": "",
      "picture": "/jpg/gallery/gallery_29.jpg"
    },
    {
      "name": "",
      "picture": "/jpg/gallery/gallery_30.jpg"
    },
    {
      "name": "",
      "picture": "/jpg/gallery/gallery_31.jpg"
    },
    {
      "name": "",
      "picture": "/jpg/gallery/gallery_32.jpg"
    },
    {
      "name": "",
      "picture": "/jpg/gallery/gallery_33.jpg"
    },
    {
      "name": "",
      "picture": "/jpg/gallery/gallery_34.jpg"
    },
    {
      "name": "",
      "picture": "/jpg/gallery/gallery_35.jpg"
    }
  ]
}